kubric/__init__.py
kubric/custom_types.py
kubric/plotting.py
kubric/post_processing.py
kubric/randomness.py
kubric/redirect_io.py
kubric/utils.py
kubric/assets/__init__.py
kubric/assets/asset_preprocessing.py
kubric/assets/asset_source.py
kubric/assets/klevr.py
kubric/core/__init__.py
kubric/core/assets.py
kubric/core/cameras.py
kubric/core/color.py
kubric/core/lights.py
kubric/core/materials.py
kubric/core/objects.py
kubric/core/scene.py
kubric/core/traits.py
kubric/core/view.py
kubric/datasets/__init__.py
kubric/datasets/katr.py
kubric/datasets/klevr.py
kubric/datasets/klevr_uni.py
kubric/renderer/__init__.py
kubric/renderer/blender.py
kubric/renderer/blender_utils.py
kubric/simulator/__init__.py
kubric/simulator/pybullet.py
test/__init__.py
test/test_blender.py
test/test_cameras.py
test/test_color.py
test/test_core.py
test/test_postprocessing.py
test/test_scene.py
test/test_traits.py
kubric-0.1.1.dist-info/LICENSE
kubric-0.1.1.dist-info/METADATA
kubric-0.1.1.dist-info/WHEEL
kubric-0.1.1.dist-info/top_level.txt
kubric-0.1.1.dist-info/RECORD
